{
  "timestamp": 1592092800000,
  "multiplier": 0.001,
  "open": 9522.12,
  "high": 9550.09,
  "low": 9522.12,
  "close": 9547.85,
  "shift": 60000,
  "times": [
    1320,
    1,
    1,
    1,
    1,
    1,
    1,
    1,
    1,
    1,
    1,
    1,
    1,
    1,
    1,
    1,
    1,
    1,
    1,
    1,
    1,
    1,
    1,
    1,
    1,
    1,
    1,
    1,
    1,
    1,
    1,
    1,
    1,
    1,
    1,
    1,
    1,
    1,
    1,
    1,
    1,
    1,
    1,
    1,
    1,
    1,
    1,
    1,
    1,
    1,
    1,
    1,
    1,
    1,
    1,
    1,
    1,
    1,
    1,
    1,
    1,
    1,
    1,
    1,
    1,
    1,
    1,
    1,
    1,
    1,
    1,
    1,
    1,
    1,
    1,
    1,
    1,
    1,
    1,
    1,
    1,
    1,
    1,
    1,
    1,
    1,
    1,
    1,
    1,
    1,
    1,
    1,
    1,
    1,
    1,
    1,
    1,
    1,
    1,
    1,
    1,
    1,
    1,
    1,
    1,
    1,
    1,
    1,
    1,
    1,
    1,
    1,
    1,
    1,
    1,
    1,
    1,
    1,
    1,
    1
  ],
  "opens": [
    0,
    22790,
    16980,
    -6800,
    5090,
    -14490,
    -13660,
    6450,
    -630,
    -18170,
    -5730,
    14910,
    -500,
    -2180,
    -4560,
    5420,
    13460,
    7420,
    3230,
    -10440,
    7410,
    -1800,
    2310,
    -2080,
    1450,
    1090,
    3940,
    6900,
    3740,
    7450,
    -2640,
    -2080,
    2290,
    -6570,
    4030,
    6540,
    1920,
    -5090,
    2630,
    -4340,
    -1700,
    -3580,
    -420,
    -8720,
    5230,
    90,
    260,
    7560,
    -890,
    4320,
    5440,
    3190,
    -2590,
    140,
    -1960,
    1520,
    -2850,
    1350,
    9660,
    -5710,
    -840,
    220,
    -2550,
    -3080,
    -5000,
    -2020,
    2600,
    2630,
    -5610,
    -80,
    -1290,
    -1140,
    2510,
    5430,
    4270,
    -1520,
    -770,
    -2310,
    -8430,
    -10580,
    -8740,
    2520,
    5010,
    -1760,
    1900,
    -2130,
    -4770,
    -5930,
    4700,
    5730,
    20,
    8380,
    1000,
    -2990,
    -920,
    4880,
    -2860,
    2660,
    10,
    5000,
    2850,
    780,
    -1410,
    -7390,
    -4610,
    3540,
    7500,
    -2880,
    1350,
    -11200,
    -5630,
    4820,
    -5140,
    -3910,
    3480,
    -1900,
    9480,
    -12040,
    -14280,
    12290
  ],
  "highs": [
    0,
    14530,
    1760,
    -1060,
    -4300,
    -13320,
    -8680,
    5680,
    -6850,
    -18170,
    11210,
    2930,
    -3200,
    -1730,
    4450,
    8550,
    8220,
    1040,
    0,
    -1650,
    1900,
    -2770,
    0,
    2500,
    -10,
    2490,
    8340,
    1720,
    11510,
    -3560,
    -920,
    -1660,
    -350,
    -2500,
    8720,
    3500,
    -3800,
    -580,
    -1880,
    -3800,
    -60,
    -3410,
    -2430,
    -1490,
    -1760,
    290,
    9720,
    -2680,
    3930,
    5880,
    2850,
    220,
    -1560,
    -1430,
    -250,
    -470,
    -1290,
    10010,
    490,
    -5400,
    1330,
    -2440,
    -2810,
    -3690,
    -3610,
    1010,
    1820,
    -790,
    -120,
    -5410,
    -590,
    2010,
    7780,
    1090,
    -890,
    820,
    -1920,
    -3440,
    -6760,
    -11380,
    -4840,
    6280,
    -560,
    -2570,
    2550,
    -4240,
    -5480,
    -1540,
    9830,
    -1530,
    6750,
    1760,
    2260,
    -6000,
    3300,
    30,
    1080,
    -680,
    4590,
    2640,
    3440,
    -1970,
    -1500,
    -5920,
    0,
    6120,
    180,
    -560,
    -1810,
    -12210,
    6160,
    -3690,
    -8510,
    660,
    -1090,
    9550,
    -1440,
    -12560,
    2190,
    13900
  ],
  "lows": [
    0,
    3940,
    26440,
    2590,
    -9930,
    -13250,
    60,
    4710,
    -17000,
    -14830,
    6320,
    16000,
    -4240,
    -1310,
    -1780,
    7200,
    13460,
    5610,
    -5400,
    0,
    5470,
    -4560,
    -260,
    5190,
    -530,
    3070,
    3740,
    6640,
    4200,
    1940,
    30,
    -930,
    -4370,
    1780,
    3510,
    6750,
    -3050,
    190,
    -3470,
    420,
    -6460,
    1480,
    -8390,
    -740,
    4110,
    -1580,
    3690,
    5940,
    1120,
    3530,
    2750,
    3270,
    -160,
    -2370,
    950,
    -1020,
    260,
    260,
    4990,
    -880,
    -1080,
    -2100,
    -3440,
    -4920,
    -4170,
    2610,
    3170,
    -2960,
    -720,
    -3300,
    -3930,
    3760,
    4250,
    4980,
    2480,
    60,
    -1760,
    -10990,
    -8720,
    -10410,
    -2450,
    6790,
    2970,
    -1460,
    1440,
    -6370,
    -6810,
    1510,
    5740,
    3660,
    2030,
    5590,
    -120,
    -3050,
    1350,
    1550,
    1290,
    1750,
    1860,
    750,
    5280,
    1100,
    -7470,
    -6030,
    1390,
    3740,
    3310,
    -2240,
    -11930,
    -2580,
    1930,
    -1610,
    -3030,
    170,
    -2570,
    4510,
    -1930,
    -16740,
    1780,
    11390
  ],
  "closes": [
    0,
    14040,
    -6800,
    5090,
    -14490,
    -13750,
    6540,
    -580,
    -18220,
    -5730,
    14910,
    -500,
    -2260,
    -4480,
    5420,
    13460,
    7420,
    3230,
    -10440,
    7410,
    -1800,
    2310,
    -2080,
    1450,
    980,
    4050,
    6900,
    3650,
    7540,
    -2950,
    -1770,
    2290,
    -6570,
    4030,
    6540,
    2100,
    -5270,
    2820,
    -4790,
    -1080,
    -3940,
    10,
    -9240,
    5320,
    90,
    260,
    7560,
    -890,
    4230,
    5530,
    3190,
    -2590,
    140,
    -2060,
    1620,
    -2740,
    1240,
    9660,
    -5510,
    -920,
    100,
    -2170,
    -3460,
    -5000,
    -1850,
    2430,
    2520,
    -5500,
    -80,
    -1290,
    -1140,
    2510,
    5430,
    4270,
    -1520,
    -770,
    -1490,
    -9250,
    -10580,
    -8380,
    2160,
    5130,
    -1880,
    1700,
    -1930,
    -4770,
    -6650,
    5150,
    6000,
    20,
    7930,
    1340,
    -3050,
    -750,
    4880,
    -2860,
    2560,
    -250,
    5360,
    2850,
    780,
    -1500,
    -7470,
    -4440,
    3540,
    7500,
    -2160,
    630,
    -11200,
    -5630,
    4290,
    -4610,
    -3960,
    3530,
    -3050,
    10630,
    -11940,
    -14030,
    12000,
    12760
  ],
  "volumes": [
    0.5565,
    0.5925,
    0.5635,
    0.50075,
    0.39625,
    0.32125,
    0.362,
    0.407,
    0.37475,
    0.48775,
    0.4835,
    0.4215,
    0.358,
    0.34175,
    0.34575,
    0.31075,
    0.3195,
    0.23025,
    0.241,
    0.28625,
    0.19725,
    0.30575,
    0.1715,
    0.20475,
    0.16425,
    0.06725,
    0.25625,
    0.14475,
    0.29975,
    0.229,
    0.25375,
    0.2015,
    0.20425,
    0.247,
    0.2155,
    0.196,
    0.1805,
    0.155,
    0.159,
    0.08875,
    0.1685,
    0.1475,
    0.2315,
    0.233,
    0.14675,
    0.15225,
    0.268,
    0.11525,
    0.19825,
    0.22375,
    0.2725,
    0.1675,
    0.116,
    0.14525,
    0.1595,
    0.09725,
    0.07775,
    0.29275,
    0.19675,
    0.145,
    0.2555,
    0.16075,
    0.2055,
    0.1675,
    0.228,
    0.19475,
    0.1155,
    0.11575,
    0.1995,
    0.18675,
    0.23725,
    0.196,
    0.2535,
    0.148,
    0.0965,
    0.11325,
    0.0875,
    0.17375,
    0.273,
    0.27475,
    0.33825,
    0.26425,
    0.2285,
    0.165,
    0.117,
    0.1055,
    0.2185,
    0.19575,
    0.24025,
    0.0995,
    0.25475,
    0.194,
    0.20725,
    0.1445,
    0.16175,
    0.143,
    0.18275,
    0.09175,
    0.16775,
    0.217,
    0.2015,
    0.09075,
    0.1875,
    0.22025,
    0.1655,
    0.258,
    0.292,
    0.2035,
    0.25225,
    0.3575,
    0.36075,
    0.322,
    0.2925,
    0.24875,
    0.23275,
    0.2455,
    0.28425,
    0.25175,
    0.30925,
    0.4005
  ]
}