{
  "timestamp": 1364169600000,
  "multiplier": 0.001,
  "open": 2800.476,
  "high": 2811.094,
  "low": 2800.476,
  "close": 2810.928,
  "shift": 60000,
  "times": [
    810,
    1,
    1,
    1,
    1,
    1,
    1,
    1,
    1,
    1,
    1,
    1,
    1,
    1,
    1,
    1,
    1,
    1,
    1,
    1,
    1,
    1,
    1,
    1,
    1,
    1,
    1,
    1,
    1,
    1,
    1,
    1,
    1,
    1,
    1,
    1,
    1,
    1,
    1,
    1,
    1,
    1,
    1,
    1,
    1,
    1,
    1,
    1,
    1,
    1,
    1,
    1,
    1,
    1,
    1,
    1,
    1,
    1,
    1,
    1,
    1,
    1,
    1,
    1,
    1,
    1,
    1,
    1,
    1,
    1,
    1,
    1,
    1,
    1,
    1,
    1,
    1,
    1,
    1,
    1,
    1,
    1,
    1,
    1,
    1,
    1,
    1,
    1,
    1,
    1,
    1,
    1,
    1,
    1,
    1,
    1,
    1,
    1,
    1,
    1,
    1,
    1,
    1,
    1,
    1,
    1,
    1,
    1,
    1,
    1,
    1,
    1,
    1,
    1,
    1,
    1,
    1,
    1,
    1,
    1,
    1,
    1,
    1,
    1,
    1,
    1,
    1,
    1,
    1,
    1,
    1,
    1,
    1,
    1,
    1,
    1,
    1,
    1,
    1,
    1,
    1,
    1,
    1,
    1,
    1,
    1,
    1,
    1,
    1,
    1,
    1,
    1,
    1,
    1,
    1,
    1,
    1,
    1,
    1,
    1,
    1,
    1,
    1,
    1,
    1,
    1,
    1,
    1,
    1,
    1,
    1,
    1,
    1,
    1,
    1,
    1,
    1,
    1,
    1,
    1,
    1,
    1,
    1,
    1,
    1,
    1,
    1,
    1,
    1,
    1,
    1,
    1,
    1,
    1,
    1,
    1,
    1,
    1,
    1,
    1,
    1,
    1,
    1,
    1,
    1,
    1,
    1,
    1,
    1,
    1,
    1,
    1,
    1,
    1,
    1,
    1,
    1,
    1,
    1,
    1,
    1,
    1,
    1,
    1,
    1,
    1,
    1,
    1,
    1,
    1,
    1,
    1,
    1,
    1,
    1,
    1,
    1,
    1,
    1,
    1,
    1,
    1,
    1,
    1,
    1,
    1,
    1,
    1,
    1,
    1,
    1,
    1,
    1,
    1,
    1,
    1,
    1,
    1,
    1,
    1,
    1,
    1,
    1,
    1,
    1,
    1,
    1,
    1,
    1,
    1,
    1,
    1,
    1,
    1,
    1,
    1,
    1,
    1,
    1,
    1,
    1,
    1,
    1,
    1,
    1,
    1,
    1,
    1,
    1,
    1,
    1,
    1,
    1,
    1,
    1,
    1,
    1,
    1,
    1,
    1,
    1,
    1,
    1,
    1,
    1,
    1,
    1,
    1,
    1,
    1,
    1,
    1,
    1,
    1,
    1,
    1,
    1,
    1,
    1,
    1,
    1,
    1,
    1,
    1,
    1,
    1,
    1,
    1,
    1,
    1,
    1,
    1,
    1,
    1,
    1,
    1,
    1,
    1,
    1,
    1,
    1,
    1,
    1,
    1,
    1,
    1,
    1,
    1,
    1,
    1,
    1,
    1,
    1,
    1,
    1,
    1,
    1,
    1,
    1,
    1,
    1,
    1,
    1,
    1,
    1,
    1,
    1,
    1,
    1,
    1,
    1,
    1,
    1,
    1,
    1,
    1,
    1,
    1,
    1,
    1,
    1,
    1,
    1,
    1,
    1,
    1,
    1,
    1,
    1,
    1,
    1
  ],
  "opens": [
    0,
    10540,
    283,
    -798,
    -1185,
    -273,
    -193,
    -1184,
    123,
    1529,
    -142,
    -466,
    128,
    -80,
    -901,
    1660,
    -282,
    1204,
    31,
    580,
    -851,
    -42,
    1000,
    432,
    -212,
    1182,
    -90,
    648,
    -529,
    -1329,
    759,
    589,
    -1088,
    -629,
    89,
    641,
    1060,
    748,
    870,
    -348,
    398,
    120,
    -1149,
    670,
    770,
    563,
    997,
    -652,
    250,
    131,
    -842,
    -1018,
    291,
    610,
    -50,
    399,
    -1178,
    -892,
    467,
    -406,
    -920,
    -142,
    -2708,
    -1231,
    -840,
    -2140,
    41,
    -611,
    161,
    1939,
    -648,
    -425,
    -576,
    -129,
    397,
    1907,
    95,
    -449,
    -662,
    119,
    240,
    -757,
    -765,
    -670,
    12,
    -568,
    -1054,
    -1066,
    -389,
    -1070,
    -820,
    -491,
    -120,
    -844,
    -745,
    -71,
    159,
    -1155,
    -605,
    672,
    379,
    590,
    765,
    85,
    -85,
    655,
    120,
    -209,
    530,
    316,
    -746,
    -44,
    -346,
    -250,
    780,
    -231,
    -645,
    -1186,
    -512,
    -931,
    -912,
    -33,
    -2260,
    -935,
    -616,
    -809,
    149,
    797,
    1043,
    251,
    560,
    270,
    569,
    -30,
    100,
    -556,
    -723,
    -180,
    619,
    241,
    27,
    -98,
    431,
    1139,
    569,
    581,
    230,
    10,
    -522,
    -886,
    -645,
    880,
    94,
    -353,
    169,
    283,
    -60,
    -848,
    -11,
    -1222,
    -990,
    392,
    -1890,
    -202,
    -678,
    -1612,
    -1161,
    -1839,
    -713,
    1133,
    -336,
    668,
    -240,
    539,
    1,
    -420,
    -190,
    919,
    855,
    -174,
    231,
    666,
    412,
    -189,
    1126,
    -386,
    -604,
    -466,
    -611,
    -469,
    162,
    290,
    774,
    634,
    960,
    1029,
    860,
    -300,
    276,
    595,
    638,
    -199,
    -490,
    -150,
    16,
    595,
    -870,
    -374,
    -337,
    78,
    993,
    400,
    478,
    -319,
    -456,
    -1516,
    272,
    151,
    309,
    51,
    109,
    -545,
    -10697,
    692,
    513,
    -1223,
    1741,
    326,
    1033,
    -913,
    253,
    799,
    497,
    1555,
    -23,
    -348,
    529,
    1570,
    702,
    139,
    -141,
    -768,
    379,
    -611,
    421,
    -860,
    -599,
    -1,
    448,
    -457,
    -220,
    -11,
    -465,
    1334,
    818,
    -167,
    997,
    -896,
    369,
    280,
    4030,
    2939,
    -138,
    -310,
    520,
    779,
    1333,
    2587,
    -1068,
    -1175,
    -147,
    -319,
    -691,
    -190,
    -245,
    475,
    790,
    -210,
    850,
    281,
    630,
    -760,
    649,
    -1321,
    -1428,
    -292,
    730,
    -129,
    150,
    1639,
    -1089,
    1079,
    309,
    -767,
    -1000,
    -80,
    -1322,
    491,
    -526,
    -54,
    -1090,
    -1509,
    315,
    -557,
    841,
    -510,
    -179,
    -890,
    -1004,
    434,
    698,
    21,
    -30,
    -251,
    1199,
    289,
    -656,
    699,
    -979,
    150,
    -51,
    -150,
    808,
    343,
    -360,
    446,
    -437,
    551,
    -740,
    0,
    467,
    -2198,
    -819,
    10,
    -1320,
    418,
    -529,
    -679,
    19,
    129,
    -1229,
    706,
    935,
    649,
    -280,
    -500,
    211,
    842,
    67,
    -930,
    -3090,
    1429,
    282,
    -1360,
    -1866,
    1126,
    -1352,
    431,
    1101,
    -694,
    264,
    1579,
    -940,
    170,
    1268,
    241,
    -209,
    -129,
    1218,
    1110,
    178,
    -508,
    -738,
    1000,
    -421,
    -1111,
    -1371,
    -747,
    609,
    350,
    -1382,
    630,
    2333,
    1160,
    -71,
    1877,
    1003,
    1159,
    -968,
    -13,
    -318
  ],
  "highs": [
    0,
    624,
    -419,
    -798,
    -732,
    -520,
    -280,
    -1303,
    1604,
    759,
    -689,
    -340,
    210,
    -414,
    813,
    81,
    703,
    345,
    261,
    459,
    -1170,
    999,
    342,
    590,
    420,
    180,
    610,
    -309,
    -532,
    -208,
    339,
    -112,
    -777,
    -481,
    419,
    985,
    536,
    1228,
    -208,
    121,
    30,
    30,
    -531,
    840,
    529,
    1101,
    101,
    -490,
    500,
    -381,
    -910,
    -701,
    711,
    70,
    250,
    -79,
    -1141,
    -260,
    -159,
    -501,
    -739,
    -330,
    -2711,
    -1099,
    -972,
    -2070,
    11,
    -539,
    1915,
    74,
    -649,
    -81,
    -920,
    121,
    2007,
    250,
    -97,
    -460,
    -551,
    451,
    -203,
    -707,
    -810,
    -220,
    -221,
    -790,
    -1054,
    -989,
    -466,
    -1042,
    -848,
    -391,
    -220,
    -739,
    -800,
    298,
    -260,
    -1068,
    -21,
    299,
    630,
    871,
    579,
    -478,
    570,
    99,
    -30,
    205,
    395,
    7,
    -556,
    -234,
    -340,
    544,
    -20,
    -41,
    -835,
    -1035,
    -663,
    -931,
    -885,
    -60,
    -2260,
    -841,
    -710,
    -560,
    587,
    1003,
    491,
    540,
    158,
    601,
    51,
    330,
    -301,
    -540,
    -659,
    356,
    364,
    -61,
    21,
    400,
    947,
    629,
    519,
    345,
    129,
    -139,
    -542,
    -878,
    12,
    388,
    -80,
    -234,
    543,
    -70,
    -169,
    -879,
    -11,
    -1171,
    -670,
    21,
    -1872,
    -220,
    -678,
    -1612,
    -1161,
    -1698,
    240,
    129,
    317,
    -5,
    199,
    31,
    0,
    -420,
    750,
    840,
    119,
    -61,
    640,
    542,
    -111,
    1190,
    -253,
    -367,
    -570,
    -470,
    -660,
    51,
    -92,
    707,
    715,
    960,
    1058,
    1031,
    -60,
    -70,
    425,
    663,
    182,
    -300,
    -510,
    231,
    279,
    -49,
    -870,
    -370,
    -91,
    820,
    451,
    430,
    -2,
    -319,
    -456,
    -1133,
    139,
    110,
    221,
    249,
    -210,
    -545,
    -10005,
    510,
    111,
    409,
    339,
    1042,
    -21,
    -649,
    768,
    571,
    1541,
    320,
    -210,
    10,
    1609,
    1121,
    60,
    -232,
    -290,
    -398,
    197,
    -397,
    19,
    -860,
    -379,
    310,
    140,
    -680,
    49,
    -100,
    681,
    746,
    204,
    657,
    352,
    -759,
    229,
    4216,
    2613,
    520,
    -508,
    169,
    696,
    2644,
    -341,
    1711,
    -1059,
    -1171,
    1,
    -480,
    -691,
    -190,
    230,
    1061,
    -260,
    720,
    410,
    435,
    34,
    160,
    -330,
    -1321,
    -1379,
    265,
    216,
    20,
    1496,
    63,
    -41,
    1212,
    -422,
    -1228,
    -970,
    -101,
    -729,
    -90,
    -110,
    -491,
    -1090,
    -840,
    -290,
    270,
    -50,
    -209,
    -480,
    -890,
    -301,
    430,
    180,
    -31,
    -159,
    940,
    341,
    415,
    -386,
    -30,
    -839,
    10,
    180,
    388,
    451,
    -69,
    80,
    129,
    -19,
    10,
    -460,
    179,
    101,
    -2291,
    -740,
    41,
    -334,
    -678,
    -508,
    -130,
    -391,
    32,
    -592,
    961,
    709,
    -30,
    -329,
    -60,
    579,
    291,
    -181,
    -900,
    -2039,
    1210,
    -590,
    -1311,
    -649,
    -101,
    -1059,
    1190,
    500,
    -671,
    1331,
    159,
    -869,
    1760,
    -133,
    162,
    -210,
    810,
    1000,
    300,
    161,
    -710,
    240,
    320,
    -661,
    -1201,
    -758,
    -740,
    335,
    174,
    -1029,
    2420,
    1310,
    -10,
    1689,
    1227,
    944,
    60,
    -262,
    -423,
    -686
  ],
  "lows": [
    0,
    10216,
    -186,
    -1590,
    57,
    -235,
    -878,
    -843,
    765,
    1370,
    -624,
    -241,
    406,
    -838,
    2,
    1356,
    22,
    971,
    182,
    -181,
    -405,
    355,
    997,
    196,
    27,
    1031,
    -123,
    217,
    -1649,
    375,
    648,
    -697,
    -283,
    -57,
    140,
    636,
    1065,
    748,
    431,
    88,
    162,
    -789,
    -1,
    670,
    436,
    855,
    367,
    -66,
    336,
    -669,
    -1193,
    133,
    291,
    442,
    86,
    -749,
    -920,
    30,
    30,
    -889,
    -202,
    -2299,
    -1500,
    -889,
    -2186,
    -136,
    -420,
    -224,
    385,
    1257,
    -755,
    8,
    -689,
    61,
    677,
    1728,
    -176,
    -882,
    -364,
    666,
    -592,
    -591,
    -556,
    -175,
    -552,
    -1003,
    -1119,
    -413,
    -979,
    -864,
    -496,
    -207,
    -773,
    -746,
    -178,
    104,
    -915,
    -685,
    -1,
    672,
    379,
    584,
    704,
    -313,
    380,
    624,
    -48,
    -123,
    643,
    -463,
    -59,
    -410,
    -251,
    113,
    408,
    -360,
    -1364,
    -394,
    -992,
    -832,
    -228,
    -2121,
    -1018,
    -570,
    -986,
    167,
    149,
    786,
    1054,
    250,
    289,
    542,
    480,
    59,
    -250,
    -1019,
    -70,
    -90,
    689,
    116,
    43,
    -30,
    472,
    1131,
    577,
    578,
    156,
    -385,
    -668,
    -640,
    -316,
    923,
    -277,
    -100,
    287,
    221,
    -700,
    -247,
    -1132,
    -889,
    -369,
    -1349,
    -93,
    -640,
    -1080,
    -1690,
    -1874,
    -1040,
    312,
    819,
    -76,
    471,
    -95,
    378,
    -144,
    -382,
    203,
    824,
    723,
    53,
    231,
    568,
    14,
    307,
    584,
    -858,
    -17,
    -645,
    -735,
    261,
    13,
    439,
    774,
    634,
    919,
    1068,
    584,
    -303,
    557,
    575,
    288,
    -520,
    -361,
    412,
    16,
    -266,
    -491,
    -410,
    75,
    184,
    960,
    348,
    171,
    -160,
    -1751,
    12,
    219,
    204,
    127,
    233,
    -394,
    -11228,
    438,
    684,
    -776,
    125,
    1649,
    418,
    124,
    -4,
    253,
    799,
    497,
    1555,
    -330,
    -41,
    529,
    1570,
    702,
    -5,
    -766,
    -11,
    -339,
    118,
    -432,
    -748,
    -30,
    171,
    -23,
    -699,
    481,
    -529,
    66,
    1326,
    -101,
    382,
    416,
    59,
    223,
    309,
    4151,
    2476,
    -99,
    -252,
    745,
    920,
    1261,
    1540,
    -911,
    -481,
    -220,
    -659,
    -765,
    74,
    246,
    447,
    448,
    158,
    762,
    281,
    -221,
    -49,
    -417,
    -1453,
    -841,
    539,
    346,
    260,
    129,
    566,
    -20,
    1109,
    -612,
    -969,
    -61,
    -1317,
    -131,
    168,
    -16,
    -1088,
    -1530,
    6,
    -838,
    598,
    330,
    -118,
    -1037,
    -1138,
    53,
    601,
    578,
    114,
    -312,
    -42,
    1219,
    -276,
    -11,
    -471,
    70,
    -74,
    -7,
    149,
    788,
    -56,
    -71,
    151,
    -200,
    2,
    -104,
    -10,
    -1609,
    -2020,
    1100,
    -1390,
    11,
    -120,
    -612,
    21,
    21,
    -1064,
    -496,
    1247,
    935,
    389,
    -750,
    -270,
    711,
    769,
    -840,
    -3040,
    -80,
    1509,
    -1300,
    -1889,
    245,
    -215,
    -11,
    424,
    366,
    -412,
    709,
    673,
    -71,
    222,
    1247,
    62,
    -199,
    10,
    1055,
    1076,
    -176,
    -645,
    -30,
    620,
    -408,
    -2081,
    -751,
    -162,
    38,
    -905,
    607,
    630,
    2188,
    639,
    595,
    1877,
    1003,
    -214,
    69,
    -328,
    -1556
  ],
  "closes": [
    0,
    366,
    -788,
    -1189,
    -64,
    -408,
    -941,
    -310,
    1676,
    -91,
    -441,
    151,
    -91,
    -943,
    1664,
    -123,
    997,
    76,
    530,
    -792,
    -156,
    1188,
    351,
    -220,
    1022,
    57,
    710,
    -560,
    -1451,
    870,
    581,
    -1080,
    -623,
    114,
    609,
    1040,
    630,
    1011,
    -350,
    398,
    112,
    -1140,
    639,
    757,
    612,
    990,
    -649,
    250,
    387,
    -1058,
    -1069,
    299,
    651,
    -110,
    415,
    -1176,
    -898,
    599,
    -520,
    -930,
    -79,
    -2422,
    -1500,
    -889,
    -2186,
    36,
    -592,
    113,
    1915,
    -570,
    -433,
    -354,
    -370,
    45,
    2234,
    169,
    -477,
    -620,
    70,
    340,
    -830,
    -723,
    -556,
    -21,
    -706,
    -1003,
    -1119,
    -392,
    -1000,
    -864,
    -496,
    -129,
    -851,
    -746,
    -44,
    186,
    -1131,
    -685,
    670,
    299,
    630,
    871,
    21,
    -145,
    723,
    121,
    -209,
    434,
    395,
    -739,
    19,
    -411,
    -258,
    799,
    -251,
    -439,
    -1390,
    -419,
    -871,
    -953,
    -126,
    -2223,
    -999,
    -589,
    -819,
    149,
    687,
    810,
    594,
    476,
    312,
    541,
    38,
    103,
    -351,
    -939,
    -150,
    596,
    261,
    10,
    -98,
    430,
    1068,
    612,
    536,
    261,
    43,
    -462,
    -668,
    -640,
    393,
    317,
    -330,
    87,
    250,
    34,
    -713,
    -147,
    -1232,
    -889,
    270,
    -1988,
    -42,
    -691,
    -1080,
    -1690,
    -1874,
    -928,
    1313,
    -294,
    681,
    -257,
    499,
    41,
    -430,
    -179,
    940,
    840,
    -191,
    240,
    649,
    460,
    -354,
    1260,
    -415,
    -580,
    -419,
    -646,
    -477,
    273,
    158,
    707,
    715,
    960,
    1058,
    841,
    -259,
    319,
    425,
    663,
    -131,
    -497,
    -271,
    212,
    519,
    -860,
    -331,
    -507,
    217,
    970,
    401,
    481,
    -321,
    -209,
    -1775,
    284,
    150,
    210,
    141,
    139,
    -523,
    -10736,
    679,
    520,
    -1240,
    1760,
    321,
    1049,
    -919,
    230,
    798,
    529,
    1542,
    251,
    -580,
    490,
    1464,
    802,
    163,
    -80,
    -850,
    371,
    -561,
    360,
    -834,
    -697,
    61,
    491,
    -460,
    -241,
    10,
    -459,
    1310,
    746,
    -97,
    958,
    -859,
    371,
    291,
    4029,
    2819,
    -50,
    -269,
    500,
    696,
    1544,
    759,
    842,
    -1161,
    -320,
    -329,
    -711,
    -189,
    -271,
    490,
    800,
    -379,
    1000,
    299,
    610,
    -750,
    980,
    -1626,
    -1453,
    -741,
    1055,
    -4,
    106,
    1630,
    -1037,
    1059,
    321,
    -799,
    -991,
    -69,
    -1300,
    500,
    -561,
    -19,
    -1088,
    -1530,
    353,
    -587,
    889,
    -559,
    -118,
    -947,
    -944,
    318,
    752,
    -75,
    67,
    -251,
    1189,
    291,
    -640,
    700,
    -1001,
    117,
    -16,
    -153,
    781,
    361,
    -330,
    430,
    -421,
    531,
    -729,
    -10,
    469,
    -2182,
    -784,
    -54,
    -1293,
    473,
    -561,
    -709,
    9,
    162,
    -1221,
    630,
    971,
    660,
    -240,
    -530,
    199,
    810,
    110,
    -939,
    -3091,
    944,
    766,
    -1379,
    -1841,
    1111,
    -1331,
    242,
    1269,
    -685,
    244,
    1601,
    -922,
    152,
    1320,
    170,
    -181,
    -129,
    1269,
    1000,
    152,
    -527,
    -645,
    999,
    -408,
    -342,
    -2148,
    -721,
    516,
    410,
    -1386,
    522,
    2429,
    1160,
    -404,
    2233,
    980,
    1191,
    -973,
    -17,
    -352,
    -1858
  ],
  "volumes": [
    0.0,
    0.0,
    0.0,
    0.0,
    0.0,
    0.0,
    0.0,
    0.0,
    0.0,
    0.0,
    0.0,
    0.0,
    0.0,
    0.0,
    0.0,
    0.0,
    0.0,
    0.0,
    0.0,
    0.0,
    0.0,
    0.0,
    0.0,
    0.0,
    0.0,
    0.0,
    0.0,
    0.0,
    0.0,
    0.0,
    0.0,
    0.0,
    0.0,
    0.0,
    0.0,
    0.0,
    0.0,
    0.0,
    0.0,
    0.0,
    0.0,
    0.0,
    0.0,
    0.0,
    0.0,
    0.0,
    0.0,
    0.0,
    0.0,
    0.0,
    0.0,
    0.0,
    0.0,
    0.0,
    0.0,
    0.0,
    0.0,
    0.0,
    0.0,
    0.0,
    0.0,
    0.0,
    0.0,
    0.0,
    0.0,
    0.0,
    0.0,
    0.0,
    0.0,
    0.0,
    0.0,
    0.0,
    0.0,
    0.0,
    0.0,
    0.0,
    0.0,
    0.0,
    0.0,
    0.0,
    0.0,
    0.0,
    0.0,
    0.0,
    0.0,
    0.0,
    0.0,
    0.0,
    0.0,
    0.0,
    0.0,
    0.0,
    0.0,
    0.0,
    0.0,
    0.0,
    0.0,
    0.0,
    0.0,
    0.0,
    0.0,
    0.0,
    0.0,
    0.0,
    0.0,
    0.0,
    0.0,
    0.0,
    0.0,
    0.0,
    0.0,
    0.0,
    0.0,
    0.0,
    0.0,
    0.0,
    0.0,
    0.0,
    0.0,
    0.0,
    0.0,
    0.0,
    0.0,
    0.0,
    0.0,
    0.0,
    0.0,
    0.0,
    0.0,
    0.0,
    0.0,
    0.0,
    0.0,
    0.0,
    0.0,
    0.0,
    0.0,
    0.0,
    0.0,
    0.0,
    0.0,
    0.0,
    0.0,
    0.0,
    0.0,
    0.0,
    0.0,
    0.0,
    0.0,
    0.0,
    0.0,
    0.0,
    0.0,
    0.0,
    0.0,
    0.0,
    0.0,
    0.0,
    0.0,
    0.0,
    0.0,
    0.0,
    0.0,
    0.0,
    0.0,
    0.0,
    0.0,
    0.0,
    0.0,
    0.0,
    0.0,
    0.0,
    0.0,
    0.0,
    0.0,
    0.0,
    0.0,
    0.0,
    0.0,
    0.0,
    0.0,
    0.0,
    0.0,
    0.0,
    0.0,
    0.0,
    0.0,
    0.0,
    0.0,
    0.0,
    0.0,
    0.0,
    0.0,
    0.0,
    0.0,
    0.0,
    0.0,
    0.0,
    0.0,
    0.0,
    0.0,
    0.0,
    0.0,
    0.0,
    0.0,
    0.0,
    0.0,
    0.0,
    0.0,
    0.0,
    0.0,
    0.0,
    0.0,
    0.0,
    0.0,
    0.0,
    0.0,
    0.0,
    0.0,
    0.0,
    0.0,
    0.0,
    0.0,
    0.0,
    0.0,
    0.0,
    0.0,
    0.0,
    0.0,
    0.0,
    0.0,
    0.0,
    0.0,
    0.0,
    0.0,
    0.0,
    0.0,
    0.0,
    0.0,
    0.0,
    0.0,
    0.0,
    0.0,
    0.0,
    0.0,
    0.0,
    0.0,
    0.0,
    0.0,
    0.0,
    0.0,
    0.0,
    0.0,
    0.0,
    0.0,
    0.0,
    0.0,
    0.0,
    0.0,
    0.0,
    0.0,
    0.0,
    0.0,
    0.0,
    0.0,
    0.0,
    0.0,
    0.0,
    0.0,
    0.0,
    0.0,
    0.0,
    0.0,
    0.0,
    0.0,
    0.0,
    0.0,
    0.0,
    0.0,
    0.0,
    0.0,
    0.0,
    0.0,
    0.0,
    0.0,
    0.0,
    0.0,
    0.0,
    0.0,
    0.0,
    0.0,
    0.0,
    0.0,
    0.0,
    0.0,
    0.0,
    0.0,
    0.0,
    0.0,
    0.0,
    0.0,
    0.0,
    0.0,
    0.0,
    0.0,
    0.0,
    0.0,
    0.0,
    0.0,
    0.0,
    0.0,
    0.0,
    0.0,
    0.0,
    0.0,
    0.0,
    0.0,
    0.0,
    0.0,
    0.0,
    0.0,
    0.0,
    0.0,
    0.0,
    0.0,
    0.0,
    0.0,
    0.0,
    0.0,
    0.0,
    0.0,
    0.0,
    0.0,
    0.0,
    0.0,
    0.0,
    0.0,
    0.0,
    0.0,
    0.0,
    0.0,
    0.0,
    0.0,
    0.0,
    0.0,
    0.0,
    0.0,
    0.0,
    0.0,
    0.0,
    0.0,
    0.0,
    0.0,
    0.0,
    0.0,
    0.0,
    0.0,
    0.0,
    0.0,
    0.0,
    0.0,
    0.0,
    0.0,
    0.0,
    0.0,
    0.0,
    0.0,
    0.0,
    0.0,
    0.0,
    0.0,
    0.0,
    0.0,
    0.0,
    0.0,
    0.0,
    0.0,
    0.0,
    0.0,
    0.0,
    0.0,
    0.0,
    0.0,
    0.0,
    0.0,
    0.0,
    0.0,
    0.0,
    0.0,
    0.0,
    0.0
  ]
}