{
  "timestamp": 1408233600000,
  "multiplier": 0.001,
  "open": 3999.895,
  "high": 3999.895,
  "low": 3999.895,
  "close": 3999.895,
  "shift": 60000,
  "times": [
    1320,
    1,
    1,
    1,
    1,
    1,
    1,
    1,
    1,
    1,
    1,
    1,
    1,
    1,
    1,
    1,
    1,
    1,
    1,
    1,
    1,
    1,
    1,
    1,
    1,
    1,
    1,
    1,
    1,
    1,
    1,
    1,
    1,
    1,
    1,
    1,
    1,
    1,
    1,
    1,
    1,
    1,
    1,
    1,
    1,
    1,
    1,
    1,
    1,
    1,
    1,
    1,
    1,
    1,
    1,
    2,
    1,
    1,
    1,
    1,
    1,
    1,
    1,
    1,
    1,
    1,
    1,
    1,
    1,
    1,
    1,
    1,
    1,
    1,
    1,
    1,
    1,
    1,
    1,
    1,
    1,
    1,
    1,
    1,
    1,
    2,
    1,
    1,
    1,
    1,
    1,
    1,
    1,
    1,
    1,
    1,
    1,
    1,
    1,
    1,
    1,
    1,
    1,
    1,
    1,
    1,
    1,
    1,
    1,
    1,
    1,
    1,
    1,
    1,
    1,
    1,
    2
  ],
  "opens": [
    0,
    -829,
    640,
    497,
    -621,
    1113,
    689,
    367,
    -505,
    1201,
    324,
    -1526,
    -430,
    -1200,
    -10,
    93,
    -37,
    402,
    -37,
    -74,
    174,
    -56,
    147,
    -85,
    539,
    197,
    -85,
    -38,
    -62,
    -7,
    -984,
    -889,
    -31,
    -129,
    16,
    593,
    222,
    237,
    361,
    91,
    -44,
    -52,
    242,
    -30,
    -83,
    -194,
    161,
    -331,
    153,
    182,
    111,
    379,
    -295,
    56,
    262,
    -246,
    -1045,
    -59,
    55,
    -160,
    10,
    338,
    -62,
    390,
    108,
    234,
    -6,
    -33,
    236,
    -275,
    67,
    -442,
    79,
    -50,
    -89,
    -248,
    200,
    148,
    -64,
    15,
    88,
    -52,
    -205,
    199,
    4,
    74,
    854,
    349,
    -293,
    291,
    -88,
    -71,
    219,
    -84,
    -398,
    51,
    -55,
    74,
    -171,
    -387,
    -27,
    30,
    -140,
    268,
    123,
    -166,
    63,
    -61,
    81,
    37,
    -281,
    -86,
    49,
    76,
    34,
    541,
    -357
  ],
  "highs": [
    0,
    -581,
    1230,
    313,
    -180,
    689,
    386,
    535,
    402,
    781,
    -291,
    -1431,
    -925,
    -1037,
    96,
    -184,
    163,
    314,
    19,
    -175,
    135,
    230,
    -167,
    403,
    60,
    188,
    -85,
    -17,
    82,
    -172,
    -984,
    -821,
    -23,
    -13,
    320,
    414,
    283,
    310,
    -90,
    297,
    -184,
    239,
    -115,
    -30,
    -83,
    -5,
    -28,
    -181,
    196,
    407,
    -73,
    145,
    -240,
    239,
    24,
    -246,
    -976,
    58,
    27,
    -318,
    471,
    1,
    566,
    -362,
    334,
    164,
    -12,
    4,
    178,
    -87,
    -250,
    -442,
    79,
    -50,
    -89,
    -18,
    166,
    -48,
    -6,
    -30,
    75,
    -52,
    63,
    -69,
    4,
    562,
    699,
    16,
    93,
    -41,
    -142,
    115,
    33,
    -84,
    -398,
    77,
    -20,
    191,
    -340,
    -12,
    -411,
    30,
    133,
    373,
    -104,
    -141,
    -113,
    -61,
    81,
    169,
    -413,
    177,
    -96,
    -9,
    358,
    245,
    -189
  ],
  "lows": [
    0,
    -1264,
    1075,
    -26,
    -135,
    621,
    1188,
    -1187,
    1079,
    1201,
    -1132,
    -259,
    -1439,
    -51,
    -98,
    84,
    -17,
    243,
    230,
    -56,
    134,
    -16,
    118,
    -56,
    463,
    267,
    -79,
    -38,
    -66,
    -581,
    -1054,
    -835,
    409,
    -88,
    26,
    696,
    -58,
    517,
    361,
    -4,
    51,
    -77,
    40,
    -17,
    -18,
    -45,
    -221,
    -77,
    281,
    182,
    55,
    37,
    103,
    56,
    -11,
    -903,
    -115,
    -59,
    -83,
    -22,
    10,
    179,
    97,
    390,
    108,
    208,
    20,
    -33,
    -320,
    170,
    130,
    -436,
    121,
    -50,
    -474,
    137,
    200,
    80,
    4,
    -357,
    460,
    -270,
    13,
    199,
    -5,
    7,
    930,
    349,
    -298,
    264,
    -430,
    303,
    219,
    -454,
    -84,
    -64,
    116,
    -140,
    -292,
    -138,
    59,
    3,
    -113,
    214,
    -103,
    -57,
    234,
    -61,
    76,
    -106,
    -133,
    -86,
    49,
    29,
    -2,
    95,
    172
  ],
  "closes": [
    0,
    -581,
    1009,
    -634,
    988,
    384,
    691,
    -997,
    1934,
    -85,
    -978,
    -515,
    -1264,
    -61,
    32,
    -183,
    98,
    249,
    165,
    -128,
    135,
    112,
    -78,
    432,
    38,
    204,
    -79,
    -17,
    82,
    -750,
    -1054,
    -261,
    -165,
    12,
    525,
    248,
    449,
    310,
    -90,
    297,
    -184,
    100,
    -15,
    -96,
    -127,
    144,
    -106,
    -103,
    196,
    134,
    101,
    61,
    -57,
    89,
    49,
    -1003,
    -94,
    58,
    -269,
    -22,
    471,
    -196,
    597,
    -196,
    334,
    -18,
    170,
    4,
    -507,
    377,
    -77,
    -436,
    121,
    -50,
    -241,
    134,
    104,
    -54,
    62,
    -30,
    75,
    -270,
    281,
    -69,
    -5,
    558,
    706,
    22,
    -4,
    -30,
    -131,
    190,
    33,
    -454,
    -84,
    133,
    -20,
    -201,
    43,
    -275,
    -139,
    3,
    137,
    276,
    -415,
    190,
    -13,
    -61,
    76,
    -106,
    -133,
    -40,
    112,
    -80,
    438,
    -201,
    257
  ],
  "volumes": [
    3e-05,
    0.000133,
    7.5e-05,
    8.2e-05,
    0.000128,
    0.000122,
    8.8e-05,
    0.000348,
    0.000105,
    0.000191,
    0.000183,
    0.000214,
    0.000106,
    3.3e-05,
    5.7e-05,
    2.6e-05,
    4.7e-05,
    0.000122,
    8.4e-05,
    1.8e-05,
    4e-05,
    7.7e-05,
    1.3e-05,
    7.9e-05,
    0.00018,
    6e-05,
    3e-05,
    6e-05,
    0.000154,
    0.000132,
    9.9e-05,
    8.3e-05,
    2.3e-05,
    4.2e-05,
    0.000107,
    4.6e-05,
    6.2e-05,
    0.0001,
    4e-05,
    0.000124,
    9e-05,
    0.00015,
    8.2e-05,
    0.000103,
    9e-05,
    6e-05,
    7.2e-05,
    2.7e-05,
    1.2e-05,
    2.6e-05,
    7.4e-05,
    3.5e-05,
    6e-06,
    1.4e-05,
    1.9e-05,
    8.1e-05,
    4e-06,
    8e-06,
    2.8e-05,
    2e-05,
    2.4e-05,
    3e-05,
    4.9e-05,
    3e-05,
    8.2e-05,
    8e-06,
    2.5e-05,
    1.2e-05,
    8.3e-05,
    3.6e-05,
    9e-06,
    1.2e-05,
    4e-06,
    4e-06,
    2.5e-05,
    1.4e-05,
    1.4e-05,
    8e-06,
    5e-06,
    1.5e-05,
    4e-06,
    1.6e-05,
    1.1e-05,
    4e-06,
    8e-06,
    3e-05,
    0.0001,
    2e-05,
    3.2e-05,
    1.6e-05,
    5.2e-05,
    1.1e-05,
    1e-05,
    1.6e-05,
    1.7e-05,
    1.5e-05,
    5e-06,
    1.2e-05,
    1.8e-05,
    0.000138,
    3e-05,
    6e-05,
    0.000282,
    7.1e-05,
    4.4e-05,
    0.000122,
    3e-05,
    3e-05,
    6e-05,
    0.000184,
    3e-05,
    0.00015,
    6.8e-05,
    2.6e-05,
    9.1e-05,
    5.1e-05,
    3.1e-05
  ]
}